rhowb-1.0.3.dist-info/licenses/LICENSE
wbdata/__init__.py
wbdata/asset/economies.json
wbdata/asset/indicators.json
wbdata/asset/regions.csv
wbdata/asset/sources.csv
wbdata/asset/topics.json
rhowb-1.0.3.dist-info/METADATA
rhowb-1.0.3.dist-info/WHEEL
rhowb-1.0.3.dist-info/top_level.txt
rhowb-1.0.3.dist-info/RECORD
