Metadata-Version: 2.4
Name: rhowb
Version: 1.0.3
Summary: Data from world bank api
Author-email: rhozhang <rhozhang@163.com>
License-Expression: MIT
Project-URL: Homepage, https://gitee.com/rhozhang/rhowb
Project-URL: Issues, https://gitee.com/rhozhang/rhowb/issues
Keywords: world bank,data
Classifier: Programming Language :: Python :: 3
Classifier: Operating System :: OS Independent
Requires-Python: >=3.12
License-File: LICENSE
Requires-Dist: polars
Dynamic: license-file
